cli/__init__.py
cli/main.py
xclock/__init__.py
xclock/edge_detection.py
xclock/errors.py
xclock/devices/__init__.py
xclock/devices/daq_device.py
xclock/devices/dummy_daq_device.py
xclock/devices/labjack_devices.py
xclock/devices/labjack_u3.py
xclock-0.2.0.dist-info/licenses/LICENSE
xclock-0.2.0.dist-info/METADATA
xclock-0.2.0.dist-info/WHEEL
xclock-0.2.0.dist-info/entry_points.txt
xclock-0.2.0.dist-info/top_level.txt
xclock-0.2.0.dist-info/RECORD
