Metadata-Version: 2.4
Name: XClock
Version: 0.2.0
Summary: Tools for synchronizing eXperimental Clocks
Author-email: Joscha Schmiedt <schmiedt@uni-bremen.de>
Maintainer-email: Joscha Schmiedt <schmiedt@uni-bremen.de>
License: MIT
Project-URL: Homepage, https://github.com/brain-bremen/XClock
Project-URL: Repository, https://github.com/brain-bremen/XClock
Project-URL: Documentation, https://github.com/brain-bremen/XClock#readme
Project-URL: Issues, https://github.com/brain-bremen/XClock/issues
Project-URL: Changelog, https://github.com/brain-bremen/XClock/releases
Keywords: synchronization,timing,experimental,daq,labjack,nidaq
Classifier: Development Status :: 3 - Alpha
Classifier: Intended Audience :: Science/Research
Classifier: License :: OSI Approved :: MIT License
Classifier: Operating System :: OS Independent
Classifier: Programming Language :: Python :: 3
Classifier: Programming Language :: Python :: 3.11
Classifier: Programming Language :: Python :: 3.12
Classifier: Programming Language :: Python :: 3.13
Classifier: Topic :: Scientific/Engineering
Classifier: Topic :: Software Development :: Libraries :: Python Modules
Requires-Python: >=3.11
License-File: LICENSE
Requires-Dist: labjack-ljm<2.0.0,>=1.23.0
Requires-Dist: labjackpython>=2.1.0
Requires-Dist: nidaqmx<2.0.0,>=1.0.2
Requires-Dist: numpy<3.0.0,>=2.2.0
Dynamic: license-file
